playwright_spy/__init__.py
playwright_spy/spy.min.js
tests/__init__.py
playwright_spy-1.0.2.dist-info/LICENSE
playwright_spy-1.0.2.dist-info/METADATA
playwright_spy-1.0.2.dist-info/WHEEL
playwright_spy-1.0.2.dist-info/top_level.txt
playwright_spy-1.0.2.dist-info/RECORD
