Metadata-Version: 2.1
Name: playwright-spy
Version: 1.0.2
Summary: A plugin for playwright to prevent detection.
Home-page: https://github.com/dsppman/playwright-spy
Author: dsppman
Author-email: dsppman@gmail.com
Classifier: Programming Language :: Python :: 3
Classifier: License :: OSI Approved :: MIT License
Classifier: Operating System :: OS Independent
Requires-Python: >=3.5
License-File: LICENSE
Requires-Dist: playwright >=1.14
